odoo8_addon_l10n_es_account_financial_report-8.0.1.0.0.99.dev11-py3.6-nspkg.pth
odoo_addons/l10n_es_account_financial_report/README.rst
odoo_addons/l10n_es_account_financial_report/__init__.py
odoo_addons/l10n_es_account_financial_report/__openerp__.py
odoo_addons/l10n_es_account_financial_report/i18n/bg.po
odoo_addons/l10n_es_account_financial_report/i18n/ca.po
odoo_addons/l10n_es_account_financial_report/i18n/ca_ES.po
odoo_addons/l10n_es_account_financial_report/i18n/cs.po
odoo_addons/l10n_es_account_financial_report/i18n/en_US.po
odoo_addons/l10n_es_account_financial_report/i18n/es.po
odoo_addons/l10n_es_account_financial_report/i18n/es_CO.po
odoo_addons/l10n_es_account_financial_report/i18n/es_CR.po
odoo_addons/l10n_es_account_financial_report/i18n/eu.po
odoo_addons/l10n_es_account_financial_report/i18n/fr.po
odoo_addons/l10n_es_account_financial_report/i18n/gl.po
odoo_addons/l10n_es_account_financial_report/i18n/hr.po
odoo_addons/l10n_es_account_financial_report/i18n/l10n_es_account_financial_report.pot
odoo_addons/l10n_es_account_financial_report/i18n/nl.po
odoo_addons/l10n_es_account_financial_report/i18n/pl.po
odoo_addons/l10n_es_account_financial_report/i18n/pt.po
odoo_addons/l10n_es_account_financial_report/i18n/pt_BR.po
odoo_addons/l10n_es_account_financial_report/i18n/ru.po
odoo_addons/l10n_es_account_financial_report/i18n/sl.po
odoo_addons/l10n_es_account_financial_report/i18n/sv.po
odoo_addons/l10n_es_account_financial_report/i18n/tr.po
odoo_addons/l10n_es_account_financial_report/i18n/vi.po
odoo_addons/l10n_es_account_financial_report/report/__init__.py
odoo_addons/l10n_es_account_financial_report/report/journal_entries_report.py
odoo_addons/l10n_es_account_financial_report/report/l10n_es_reports.xml
odoo_addons/l10n_es_account_financial_report/static/description/icon.png
odoo_addons/l10n_es_account_financial_report/static/description/icon.svg
odoo_addons/l10n_es_account_financial_report/tests/__init__.py
odoo8_addon_l10n_es_account_financial_report-8.0.1.0.0.99.dev11.dist-info/METADATA
odoo8_addon_l10n_es_account_financial_report-8.0.1.0.0.99.dev11.dist-info/WHEEL
odoo8_addon_l10n_es_account_financial_report-8.0.1.0.0.99.dev11.dist-info/namespace_packages.txt
odoo8_addon_l10n_es_account_financial_report-8.0.1.0.0.99.dev11.dist-info/top_level.txt
odoo8_addon_l10n_es_account_financial_report-8.0.1.0.0.99.dev11.dist-info/RECORD
